pyboot/dataflowx/context/redis/__init__.py
pyboot/dataflowx/context/redis/redis.py
pyboot_redis-1.3.3.dist-info/licenses/LICENSE
pyboot_redis-1.3.3.dist-info/METADATA
pyboot_redis-1.3.3.dist-info/WHEEL
pyboot_redis-1.3.3.dist-info/top_level.txt
pyboot_redis-1.3.3.dist-info/RECORD
